invoke_agent/__init__.py
invoke_agent/agent.py
invoke_agent/auth.py
invoke_agent/compile.py
invoke_agent/context.py
invoke_agent/core.py
invoke_agent/io.py
invoke_agent-0.1.3.dist-info/licenses/LICENSE
invoke_agent-0.1.3.dist-info/METADATA
invoke_agent-0.1.3.dist-info/WHEEL
invoke_agent-0.1.3.dist-info/top_level.txt
invoke_agent-0.1.3.dist-info/RECORD
