Metadata-Version: 2.4
Name: invoke-agent
Version: 0.1.3
Summary: A lightweight API execution layer for LLM agents.
Author: mercury0100
License: MIT
Project-URL: Homepage, https://github.com/mercury0100/invoke
Project-URL: Issues, https://github.com/mercury0100/invoke/issues
Classifier: Programming Language :: Python :: 3
Classifier: License :: OSI Approved :: MIT License
Classifier: Operating System :: OS Independent
Requires-Python: >=3.8
License-File: LICENSE
Requires-Dist: requests
Requires-Dist: python-dotenv
Requires-Dist: tldextract
Requires-Dist: pyyaml
Requires-Dist: langchain-core
Requires-Dist: langchain
Requires-Dist: authlib
Dynamic: license-file
